tabmixer/__init__.py
tabmixer/tabmixer.py
TabMixer-0.1.0.dist-info/METADATA
TabMixer-0.1.0.dist-info/WHEEL
TabMixer-0.1.0.dist-info/top_level.txt
TabMixer-0.1.0.dist-info/RECORD
