Metadata-Version: 2.1
Name: TabMixer
Version: 0.1.0
Summary: A TabMixer module for mixing tabular data using MLP blocks
Home-page: https://github.com/yourusername/TabMixer
Author: Your Name
Author-email: your.email@example.com
Classifier: Programming Language :: Python :: 3
Classifier: License :: OSI Approved :: MIT License
Classifier: Operating System :: OS Independent
Requires-Python: >=3.6
Requires-Dist: torch (>=1.8.0)
